h3result-1.0.5.dist-info/WHEEL
h3result-1.0.5.dist-info/METADATA
h3result-1.0.5.dist-info/RECORD
h3result/read_h3result.py
h3result/_cffi.cpython-39-x86_64-linux-gnu.so
h3result/__init__.py
h3result/_cffi.c
h3result/error.py
h3result/_cffi.o
h3result/path_like.py
h3result/h3result.py
h3result/interface.h
h3result/_cffi.cpython-311-x86_64-linux-musl.so
h3result/_cffi.cpython-310-x86_64-linux-gnu.so
h3result/lib/libh3result.a
h3result/lib/liblio.a
h3result/lib/liblite_pack.a
h3result/include/h3r_hit.h
h3result/include/h3r_tophits.h
h3result/include/h3r_alidisplay.h
h3result/include/h3r_result.h
h3result/include/h3r_zsetby.h
h3result/include/h3r_domain.h
h3result/include/h3r_stats.h
h3result/include/lio.h
h3result/include/lite_pack.h
