Metadata-Version: 2.3
Name: h3result
Version: 1.0.5
Summary: Python wrapper for h3result library.
License: MIT
Author: Danilo Horta
Author-email: horta@ebi.ac.uk
Requires-Python: >=3.9,<4.0
Classifier: License :: OSI Approved :: MIT License
Classifier: Programming Language :: Python :: 3
Classifier: Programming Language :: Python :: 3.9
Classifier: Programming Language :: Python :: 3.10
Classifier: Programming Language :: Python :: 3.11
Classifier: Programming Language :: Python :: 3.12
Classifier: Programming Language :: Python :: 3.13
Requires-Dist: cffi (>=1.17,<2.0)
